pythonweb/pythonweb.py
highghlow_pythonweb-1.0.0.dist-info/LICENCE.md
highghlow_pythonweb-1.0.0.dist-info/METADATA
highghlow_pythonweb-1.0.0.dist-info/WHEEL
highghlow_pythonweb-1.0.0.dist-info/top_level.txt
highghlow_pythonweb-1.0.0.dist-info/RECORD
