Metadata-Version: 2.1
Name: highghlow-pythonweb
Version: 1.0.0
Summary: A Flask wrapper for easy RESTful api development
Author-email: Highghlow <highghlow@proton.me>
Project-URL: Homepage, https://github.com/highghlow/PythonWEB
Project-URL: Bug Tracker, https://github.com/highghlow/PythonWEB/issues
Classifier: Programming Language :: Python :: 3
Classifier: License :: OSI Approved :: MIT License
Classifier: Operating System :: OS Independent
Requires-Python: >=3.7
License-File: LICENCE.md
Requires-Dist: flask <3.0,>=2.0.0
